zhangbin_test1/__init__.py
zhangbin_test1/zhangbin_test1.py
zhangbin_test1-0.0.3.dist-info/LICENSE
zhangbin_test1-0.0.3.dist-info/METADATA
zhangbin_test1-0.0.3.dist-info/WHEEL
zhangbin_test1-0.0.3.dist-info/top_level.txt
zhangbin_test1-0.0.3.dist-info/RECORD
