Metadata-Version: 2.1
Name: zhangbin-test1
Version: 0.0.3
Summary: just my testing file to add someday
Home-page: https://github.com/stevenbin/zhangbin
Author: zhangbin
Author-email: zbaa112233@qq.com
License: UNKNOWN
Platform: UNKNOWN
Classifier: Programming Language :: Python :: 3
Classifier: License :: OSI Approved :: MIT License
Classifier: Operating System :: OS Independent
